{
  "schema_version": 1,
  "program": "CanonicalEvent",
  "charter_version": "1.0.0",
  "roadmap_version": "1.0.0",
  "as_of": "2026-07-21T17:40:00+02:00",
  "repository": "utekos-brand/utekos-headless",
  "git": {
    "origin_main_reported": "0a800b1ae169eab8af12c21b3595fe99a667d54c",
    "local_ahead_by_reported": 17,
    "local_head_pushed": false,
    "local_head_deployed": false,
    "production_deployment_id": "dpl_ETtmNLjSG4vjUSj1owVEUmhScEw1",
    "production_deployment_sha": "0a800b1ae169eab8af12c21b3595fe99a667d54c",
    "production_deployment_state": "READY",
    "rollback_sha": "ee781aed52474eb6bdecee63e43ffabec9d0cea2",
    "docs_push_deferred": true,
    "verification_required_before_write": true,
    "local_head_reported": "b2cd690372bf8ee188f0a711abe60dc200039cef",
    "expected_parent_for_next_task": "b2cd690372bf8ee188f0a711abe60dc200039cef"
  },
  "progress": {
    "accepted_points": 31,
    "implemented_points": 31,
    "production_verified_points": 26,
    "total_points": 100,
    "phase_1_status": "ACCEPTED_WITH_NONBLOCKING_OBSERVATIONS",
    "phase_2_status": "IN_PROGRESS"
  },
  "current_governance_task": null,
  "next_runtime_task": "CE-2.3B",
  "current_runtime_status": "CE_2_3B_AUTHORIZED",
  "last_accepted_runtime_task": "CE-2.3A-F1",
  "last_accepted_runtime_sha": "59c130c2ee9c93c3f62332fa03763d27e5168b05",
  "last_accepted_governance_task": "CE-2.3A-F1",
  "ce_2_2": {
    "status": "ACCEPTED_SUPERSEDED_FOR_IMPLEMENTATION",
    "decision": "DEC-010",
    "owner_accepted": true
  },
  "ce_2_2a": {
    "status": "SUPERSEDED_BY_CE_2_2B",
    "tip_sha": "998a22efd414309e1cb1187535cebc0768c9dac9",
    "decision_amendment": "DEC-011",
    "purchase": "SHOP_SPECIFIC_WEBHOOK_PLUS_RECONCILIATION",
    "refund": "SHOP_SPECIFIC_WEBHOOK_PLUS_RECONCILIATION"
  },
  "ce_2_2b": {
    "status": "ACCEPTED",
    "owner_accepted": true,
    "accepted_at": "2026-07-21T17:21:00+02:00",
    "accepted_commit": "b445e9f8cfbc17bc4f01b576e23d3bfa2b407422",
    "purchase": "SHOP_ADMIN_NOTIFICATION_WEBHOOK_PLUS_RECONCILIATION",
    "refund": "SHOP_ADMIN_NOTIFICATION_WEBHOOK_PLUS_RECONCILIATION",
    "decision": "DEC-012",
    "decision_status": "APPROVED",
    "decision_title": "Shopify Admin notification webhooks own Purchase and Refund",
    "orders_paid": {
      "surface": "Shopify Admin → Settings → Notifications → Webhooks",
      "event": "Order payment",
      "destination": "https://utekos.no/api/shopify/webhooks/orders-paid",
      "format": "JSON",
      "webhook_api_version": "2026-04",
      "signing_secret_env": "SHOPIFY_WEBHOOK_SECRET",
      "visible_in_webhookSubscriptions": false,
      "status": "LIVE_PRODUCTION_PROVEN"
    },
    "refunds_create": {
      "surface": "Shopify Admin → Settings → Notifications → Webhooks",
      "event": "Refund create",
      "destination": "https://utekos.no/api/shopify/webhooks/refunds-create",
      "format": "JSON",
      "webhook_api_version": "2026-04",
      "signing_secret_env": "SHOPIFY_WEBHOOK_SECRET",
      "status": "LIVE_SUBSCRIPTION",
      "graphql_create": "FORBIDDEN"
    },
    "mode_a": "NOT_APPLICABLE",
    "mode_b_graphql_create": "FORBIDDEN",
    "toml_or_app_deploy_owns_subscriptions": false,
    "utekos_storefront_token_role": "identity_and_reconciliation_not_notification_owner",
    "mutation_performed": false
  },
  "ce_2_3a": {
    "status": "ACCEPTED",
    "conclusion": "SUBSCRIPTIONS_ESTABLISHED_WITH_PAYLOAD_BLOCKER",
    "evidence": "docs/analytics/evidence/ce-2.3a-notification-webhook-post-mutation-verification.md",
    "evidence_commit": "0787af63a25fe71375b555854e8384743c9020f5",
    "secret_fingerprint_prefix": "8a75081095f1",
    "payload_blocker": null,
    "orders_paid_live": true,
    "refunds_create_live_subscription": true,
    "refunds_create_ledger_rows": 0,
    "graphql_subscription_create": "FORBIDDEN",
    "mutation_performed_by_agent": false,
    "owner_accepted": true,
    "accepted_at": "2026-07-21T17:21:00+02:00"
  },
  "ce_2_3a_f1": {
    "status": "ACCEPTED",
    "conclusion": "REFUND_2026_04_COMPATIBILITY_FIXED",
    "accepted_runtime_sha": "59c130c2ee9c93c3f62332fa03763d27e5168b05",
    "stop_refund_2026_04_payload_incompatible": "CLOSED",
    "stop_active_double_count_risk": "ACTIVE",
    "owner_accepted": true,
    "accepted_at": "2026-07-21T17:40:00+02:00",
    "status_commit_sha": "b2cd690372bf8ee188f0a711abe60dc200039cef"
  },
  "active_interlocks": [
    "SAFE-001_META_PURCHASE_REPLAY",
    "SAFE-002_SHOPIFY_OWNER_UNPROVEN",
    "SAFE-003_GOOGLE_NATIVE_ADS_OWNER_UNKNOWN",
    "STOP_ACTIVE_DOUBLE_COUNT_RISK"
  ],
  "known_release_blockers": [
    "Local docs commits deferred from separate push",
    "STOP_ACTIVE_DOUBLE_COUNT_RISK webhook∩server distinct event_ids"
  ],
  "authoritative_files": [
    "docs/analytics/program-charter.md",
    "docs/analytics/roadmap.md",
    "docs/analytics/decision-log.md",
    "docs/analytics/current-handoff.md"
  ],
  "last_accepted_governance_sha": "b2cd690372bf8ee188f0a711abe60dc200039cef"
}
